ma2l/__init__.py
ma2l/app.py
ma2l/common.py
ma2l/fmk.py
ma2l/py.typed
ma2l/rank_table.py
ma2l-0.1.2.dist-info/LICENSE
ma2l-0.1.2.dist-info/METADATA
ma2l-0.1.2.dist-info/WHEEL
ma2l-0.1.2.dist-info/entry_points.txt
ma2l-0.1.2.dist-info/RECORD
