Metadata-Version: 2.1
Name: ma2l
Version: 0.1.2
Summary: 
Home-page: https://github.com/geniuspatrick/ma2l
License: MIT
Author: Genius Patrick
Author-email: 74176172+geniuspatrick@users.noreply.github.com
Requires-Python: >=3.7,<4.0
Classifier: Development Status :: 2 - Pre-Alpha
Classifier: Intended Audience :: Developers
Classifier: License :: OSI Approved :: MIT License
Classifier: Natural Language :: English
Classifier: Programming Language :: Python :: 3
Classifier: Programming Language :: Python :: 3.7
Classifier: Programming Language :: Python :: 3.8
Classifier: Programming Language :: Python :: 3.9
Classifier: Programming Language :: Python :: 3.10
Classifier: Programming Language :: Python :: 3.11
Classifier: Programming Language :: Python :: 3.12
Provides-Extra: dev
Provides-Extra: doc
Provides-Extra: test
Requires-Dist: black (==23.1.0) ; extra == "dev"
Requires-Dist: flake8 (==5.0.4) ; extra == "dev"
Requires-Dist: flake8-typing-imports (>=1.14.0,<2.0.0) ; extra == "dev"
Requires-Dist: isort (==5.11.5) ; extra == "dev"
Requires-Dist: mike (>=1.1.2,<2.0.0) ; extra == "doc"
Requires-Dist: mkdocs (>=1.2.3,<2.0.0) ; extra == "doc"
Requires-Dist: mkdocs-autorefs (>=0.3.1,<0.4.0) ; extra == "doc"
Requires-Dist: mkdocs-include-markdown-plugin (>=3.2.3,<4.0.0) ; extra == "doc"
Requires-Dist: mkdocs-material (>=8.1.11,<9.0.0) ; extra == "doc"
Requires-Dist: mkdocs-material-extensions (>=1.0.3,<2.0.0) ; extra == "doc"
Requires-Dist: mkdocstrings (>=0.18.0,<0.19.0) ; extra == "doc"
Requires-Dist: pkginfo (>=1.9,<2.0) ; extra == "doc"
Requires-Dist: pre-commit (>=2.17.0,<3.0.0) ; extra == "dev"
Requires-Dist: pytest (>=7.0.1,<8.0.0) ; extra == "test"
Requires-Dist: pytest-cov (>=3.0.0,<4.0.0) ; extra == "test"
Requires-Dist: setuptools (>=68.0,<69.0) ; extra == "doc"
Requires-Dist: toml (>=0.10.2,<0.11.0) ; extra == "dev"
Requires-Dist: tox (>=3.24.5,<4.0.0) ; extra == "dev"
Requires-Dist: twine (>=3.8.0,<4.0.0) ; extra == "dev"
Requires-Dist: virtualenv (>=20.0,<21.0) ; extra == "doc"
